iikoserver_api/__init__.py
iikoserver_api/iiko_server_api.py
iikoserver_api/request_manager.py
iikoserver_api/schemas/__init__.py
iikoserver_api/schemas/account.py
iikoserver_api/schemas/cashshift.py
iikoserver_api/schemas/conception.py
iikoserver_api/schemas/corporation.py
iikoserver_api/schemas/employee.py
iikoserver_api/schemas/implementation_act.py
iikoserver_api/schemas/incoming_invoice.py
iikoserver_api/schemas/incoming_service.py
iikoserver_api/schemas/inventory.py
iikoserver_api/schemas/nomenclature_group.py
iikoserver_api/schemas/outgoing_invoice.py
iikoserver_api/schemas/outgoing_service.py
iikoserver_api/schemas/product.py
iikoserver_api/schemas/returning_invoice.py
iikoserver_api/schemas/write_off.py
iikoserver_api/services/__init__.py
iikoserver_api/services/implementation_act_builder.py
iikoserver_api/services/incoming_service_builder.py
iikoserver_api/services/inventory_document_builder.py
iikoserver_api/services/olap_cash_shift_builder.py
iikoserver_api/services/outgoing_service_builder.py
iikoserver_api/services/returning_invoice_builder.py
iikoserver_api-0.0.49.dist-info/METADATA
iikoserver_api-0.0.49.dist-info/WHEEL
iikoserver_api-0.0.49.dist-info/top_level.txt
iikoserver_api-0.0.49.dist-info/RECORD
