Metadata-Version: 2.1
Name: iikoserver_api
Version: 0.0.49
Summary: iikoserver api connector
Home-page: https://github.com/sizlik/iikoserver_api
Author: Eugene
Author-email: zenjagems@gmail.com
Classifier: Programming Language :: Python :: 3
Classifier: License :: OSI Approved :: MIT License
Classifier: Operating System :: OS Independent
Requires-Python: >=3.12
Requires-Dist: pydantic >=2.0.0
Requires-Dist: requests >=2.22.0
Requires-Dist: xmltodict >=0.12.0
